Final Project/RV32IMF Processor/SQRT_FP.v
module SQRT_FP #(
    parameter WIDTH = 32,                       // width of radicand
    parameter FBITS = 10                        // fractional bits (for fixed point)
    ) 
(
    input clk,
    input start,                                // start signal
    input [WIDTH - 1 : 0] rad,                  // radicand


    output reg busy,                            // calculation in progress
    output reg valid,                           // root and rem are valid
    output reg [WIDTH - 1 : 0] root,            // root
    output reg [WIDTH - 1 : 0] rem              // remainder
    );

    reg [WIDTH - 1 : 0] x, x_next;              // radicand copy
    reg [WIDTH - 1 : 0] q, q_next;              // intermediate root (quotient)
    reg [WIDTH + 1 : 0] ac, ac_next;            // accumulator (2 bits wider)
    reg [WIDTH + 1 : 0] test_res;               // sign test result (2 bits wider)

    localparam ITER = (WIDTH + FBITS) >> 1;     // iterations are half radicand+fbits width
    reg [4 : 0] i;                              // iteration counter

    always @(*)
    begin
        test_res = ac - {q, 2'b01};

        if (test_res[WIDTH + 1] == 0) 
        begin  // test_res ≥0? (check MSB)
            {ac_next, x_next} = {test_res[WIDTH - 1 : 0], x, 2'b0};
            q_next = {q[WIDTH - 2 : 0], 1'b1};
        end 
        else 
        begin
            {ac_next, x_next} = {ac[WIDTH - 1 : 0], x, 2'b0};
            q_next = q << 1;
        end
    end

    always @(posedge clk) 
    begin
        if (start) 
        begin
            busy <= 1;
            valid <= 0;
            i <= 0;
            q <= 0;
            {ac, x} <= {{WIDTH{1'b0}}, rad, 2'b0};
        end 
        
        else if (busy) 
        begin

            if (i == ITER-1) 
            begin  // we're done
                busy <= 0;
                valid <= 1;
                root <= q_next;
                rem <= ac_next[WIDTH + 1 : 2];  // undo final shift
            end

            else 
            begin  // next iteration
                i <= i + 1;
                x <= x_next;
                ac <= ac_next;
                q <= q_next;
            end
        end
    end
endmodule

Verilog Assignments/Verilog Assignments Answers/Verilog HW2/C) SQRT_FP/SQRT_FP_tb.v
// Computer Organization - IUST Spring 2023
// Verilog HW2 : 3
//-----------------------------------------
// Squared Root Fixed-Point testbench

`include "SQRT_FP.v"
module sqrt_fp_tb();

    parameter CLK_PERIOD = 10;
    parameter WIDTH = 32;
    parameter FBITS = 10;
    parameter SF = 2.0**-10.0;  // Q8.8 scaling factor is 2^-10

    reg clk;
    reg start;              // start signal
    wire busy;              // calculation in progress
    wire valid;             // root and rem are valid
    reg  [WIDTH-1:0] rad;   // radicand
    wire [WIDTH-1:0] root;  // root
    wire [WIDTH-1:0] rem;   // remainder

    
    SQRT_FP sqrt(clk, start, rad, busy, valid, root, rem);

    always #(CLK_PERIOD / 2) clk = ~clk;


    initial begin
        $dumpfile("SQRT_FP.vcd");
        $dumpvars(0,sqrt_fp_tb);

        clk = 1;
        #100    rad = 8'b00000000;  // 0
                start = 1;
        #10     start = 0;

        #50     rad = 8'b00000001;  // 1
                start = 1;
        #10     start = 0;

        #50     rad = 8'b01111001;  // 121
                start = 1;
        #10     start = 0;

        #50     rad = 8'b01010001;  // 81
                start = 1;
        #10     start = 0;

        #50     rad = 8'b01011010;  // 90
                start = 1;
        #10     start = 0;

        #50     rad = 8'b11111111;  // 255
                start = 1;
        #10     start = 0;

        #10000    $finish;
    end
endmodule

Verilog_Assignments/Verilog_HW2/Solutions/3_Square_Root_Fixed_Point/Square_Root.vcd
$date
	Wed May 31 12:28:18 2023
$end
$version
	Icarus Verilog
$end
$timescale
	1s
$end
$scope module sqrt_fp_tb $end
$var wire 1 ! valid $end
$var wire 32 " root [31:0] $end
$var wire 32 # rem [31:0] $end
$var wire 1 $ busy $end
$var parameter 32 % CLK_PERIOD $end
$var parameter 32 & FBITS $end
$var real 1 ' SF $end
$var parameter 32 ( WIDTH $end
$var reg 1 ) clk $end
$var reg 32 * rad [31:0] $end
$var reg 1 + start $end
$scope module sqrt $end
$var wire 1 ) clk $end
$var wire 32 , rad [31:0] $end
$var wire 1 + start $end
$var parameter 32 - FBITS $end
$var parameter 32 . ITER $end
$var parameter 32 / WIDTH $end
$var reg 34 0 ac [33:0] $end
$var reg 34 1 ac_next [33:0] $end
$var reg 1 $ busy $end
$var reg 5 2 i [4:0] $end
$var reg 32 3 q [31:0] $end
$var reg 32 4 q_next [31:0] $end
$var reg 32 5 rem [31:0] $end
$var reg 32 6 root [31:0] $end
$var reg 34 7 test_res [33:0] $end
$var reg 1 ! valid $end
$var reg 32 8 x [31:0] $end
$var reg 32 9 x_next [31:0] $end
$upscope $end
$upscope $end
$enddefinitions $end
$comment Show the parameter values. $end
$dumpall
b100000 /
b10101 .
b1010 -
b100000 (
r0.0009765625 '
b1010 &
b1010 %
$end
#0
$dumpvars
bx 9
bx 8
bx 7
bx 6
bx 5
bx 4
bx 3
bx 2
bx 1
bx 0
bx ,
x+
bx *
1)
x$
bx #
bx "
x!
$end
#5
0)
#10
1)
#15
0)
#20
1)
#25
0)
#30
1)
#35
0)
#40
1)
#45
0)
#50
1)
#55
0)
#60
1)
#65
0)
#70
1)
#75
0)
#80
1)
#85
0)
#90
1)
#95
0)
#100
b0 4
b0 1
b0 9
b1111111111111111111111111111111111 7
b0 0
b0 8
b0 3
b0 2
0!
1$
1)
1+
b0 *
b0 ,
#105
0)
#110
b1 2
1)
0+
#115
0)
#120
b10 2
1)
#125
0)
#130
b11 2
1)
#135
0)
#140
b100 2
1)
#145
0)
#150
b101 2
1)
#155
0)
#160
b10000 9
b100 8
b0 2
1)
1+
b1 *
b1 ,
#165
0)
#170
b1000000 9
b10000 8
b1 2
1)
0+
#175
0)
#180
b100000000 9
b1000000 8
b10 2
1)
#185
0)
#190
b10000000000 9
b100000000 8
b11 2
1)
#195
0)
#200
b1000000000000 9
b10000000000 8
b100 2
1)
#205
0)
#210
b100000000000000 9
b1000000000000 8
b101 2
1)
#215
0)
#220
b11110010000 9
b111100100 8
b0 2
1)
1+
b1111001 *
b1111001 ,
#225
0)
#230
b1111001000000 9
b11110010000 8
b1 2
1)
0+
#235
0)
#240
b111100100000000 9
b1111001000000 8
b10 2
1)
#245
0)
#250
b11110010000000000 9
b111100100000000 8
b11 2
1)
#255
0)
#260
b1111001000000000000 9
b11110010000000000 8
b100 2
1)
#265
0)
#270
b111100100000000000000 9
b1111001000000000000 8
b101 2
1)
#275
0)
#280
b10100010000 9
b101000100 8
b0 2
1)
1+
b1010001 *
b1010001 ,
#285
0)
#290
b1010001000000 9
b10100010000 8
b1 2
1)
0+
#295
0)
#300
b101000100000000 9
b1010001000000 8
b10 2
1)
#305
0)
#310
b10100010000000000 9
b101000100000000 8
b11 2
1)
#315
0)
#320
b1010001000000000000 9
b10100010000000000 8
b100 2
1)
#325
0)
#330
b101000100000000000000 9
b1010001000000000000 8
b101 2
1)
#335
0)
#340
b10110100000 9
b101101000 8
b0 2
1)
1+
b1011010 *
b1011010 ,
#345
0)
#350
b1011010000000 9
b10110100000 8
b1 2
1)
0+
#355
0)
#360
b101101000000000 9
b1011010000000 8
b10 2
1)
#365
0)
#370
b10110100000000000 9
b101101000000000 8
b11 2
1)
#375
0)
#380
b1011010000000000000 9
b10110100000000000 8
b100 2
1)
#385
0)
#390
b101101000000000000000 9
b1011010000000000000 8
b101 2
1)
#395
0)
#400
b111111110000 9
b1111111100 8
b0 2
1)
1+
b11111111 *
b11111111 ,
#405
0)
#410
b11111111000000 9
b111111110000 8
b1 2
1)
0+
#415
0)
#420
b1111111100000000 9
b11111111000000 8
b10 2
1)
#425
0)
#430
b111111110000000000 9
b1111111100000000 8
b11 2
1)
#435
0)
#440
b11111111000000000000 9
b111111110000000000 8
b100 2
1)
#445
0)
#450
b1111111100000000000000 9
b11111111000000000000 8
b101 2
1)
#455
0)
#460
b111111110000000000000000 9
b1111111100000000000000 8
b110 2
1)
#465
0)
#470
b11111111000000000000000000 9
b111111110000000000000000 8
b111 2
1)
#475
0)
#480
b1111111100000000000000000000 9
b11111111000000000000000000 8
b1000 2
1)
#485
0)
#490
b111111110000000000000000000000 9
b1111111100000000000000000000 8
b1001 2
1)
#495
0)
#500
b11111111000000000000000000000000 9
b111111110000000000000000000000 8
b1010 2
1)
#505
0)
#510
b11 1
b11111100000000000000000000000000 9
b11111111000000000000000000000000 8
b1011 2
1)
#515
0)
#520
b1 4
b1011 1
b11110000000000000000000000000000 9
b10 7
b11 0
b11111100000000000000000000000000 8
b1100 2
1)
#525
0)
#530
b11 4
b11011 1
b11000000000000000000000000000000 9
b110 7
b1 3
b1011 0
b11110000000000000000000000000000 8
b1101 2
1)
#535
0)
#540
b111 4
b111011 1
b0 9
b1110 7
b11 3
b11011 0
b11000000000000000000000000000000 8
b1110 2
1)
#545
0)
#550
b1111 4
b1111000 1
b11110 7
b111 3
b111011 0
b0 8
b1111 2
1)
#555
0)
#560
b11111 4
b11101100 1
b111011 7
b1111 3
b1111000 0
b10000 2
1)
#565
0)
#570
b111111 4
b110111100 1
b1101111 7
b11111 3
b11101100 0
b10001 2
1)
#575
0)
#580
b1111111 4
b1011111100 1
b10111111 7
b111111 3
b110111100 0
b10010 2
1)
#585
0)
#590
b11111111 4
b1111111100 1
b11111111 7
b1111111 3
b1011111100 0
b10011 2
1)
#595
0)
#600
b111111110 4
b111111110000 1
b1111111111111111111111111111111111 7
b11111111 3
b1111111100 0
b10100 2
1)
#605
0)
#610
b1111111100 #
b1111111100 5
b111111110 "
b111111110 6
1!
0$
1)
