Verilog Assignments/Verilog Assignments Answers/Verilog HW0/HW0 (Bonus Point)/Fibonacci_Sequence.v
// Computer Organization - IUST Spring 2023
// Verilog HW0 : 2
//-----------------------------------------
// Fibonacci Sequence

`timescale 1ns / 1ps
module fibonacci (clk, rst, out); input clk;
  input rst;
  output [11:0] out;
  reg [11:0] previous_val;
  reg [11:0] current_val;

  always @(posedge clk or posedge rst)
  begin
      if (rst == 1'b1)
      begin
        previous_val <= 12'b0;
        current_val <= 12'b1;
      end
      else if (clk == 1'b1)
      begin
        previous_val <= current_val;
        current_val<= current_val + previous_val;
      end
  end
  assign out = previous_val;
endmodule

Verilog Assignments/Verilog Assignments Answers/Verilog HW0/HW0 (Bonus Point)/Fibonacci_tb.v
// Computer Organization - IUST Spring 2023
// Verilog HW0 : 2
//-----------------------------------------
// Fibonacci Sequence testbench

`include "Fibonacci_Sequence.v"
module fibonacci_tb ();
  
  reg clk, en, rst;
  wire [11:0] out;
  fibonacci F1 (clk, rst, out);
  
  always #1 clk = ~clk;
  
  initial begin
    clk = 0; rst = 1; en = 0;
    #2 rst = 0; en = 0;
    #2 en = 1;
    #30 en = 0;
    #2 en = 1;
    #40 $stop;
  end

  initial begin
    $dumpfile("fibonacci.vcd");
    $dumpvars(0,fibonacci_tb);
  end
  
endmodule

Verilog Assignments/Verilog Assignments Answers/Verilog HW0/HW0 (Bonus Point)/fibonacci.vcd
$date
	Fri Mar 17 15:00:01 2023
$end
$version
	Icarus Verilog
$end
$timescale
	1ps
$end
$scope module fibonacci_tb $end
$var wire 12 ! out [11:0] $end
$var reg 1 " clk $end
$var reg 1 # en $end
$var reg 1 $ rst $end
$scope module F1 $end
$var wire 1 " clk $end
$var wire 12 % out [11:0] $end
$var wire 1 $ rst $end
$var reg 12 & current_val [11:0] $end
$var reg 12 ' previous_val [11:0] $end
$upscope $end
$upscope $end
$enddefinitions $end
$comment Show the parameter values. $end
$dumpall
$end
#0
$dumpvars
b0 '
b1 &
b0 %
1$
0#
0"
b0 !
$end
#1000
1"
#2000
0"
0$
#3000
b1 !
b1 %
b1 '
1"
#4000
0"
1#
#5000
b10 &
1"
#6000
0"
#7000
b11 &
b10 !
b10 %
b10 '
1"
#8000
0"
#9000
b101 &
b11 !
b11 %
b11 '
1"
#10000
0"
#11000
b1000 &
b101 !
b101 %
b101 '
1"
#12000
0"
#13000
b1101 &
b1000 !
b1000 %
b1000 '
1"
#14000
0"
#15000
b10101 &
b1101 !
b1101 %
b1101 '
1"
#16000
0"
#17000
b100010 &
b10101 !
b10101 %
b10101 '
1"
#18000
0"
#19000
b110111 &
b100010 !
b100010 %
b100010 '
1"
#20000
0"
#21000
b1011001 &
b110111 !
b110111 %
b110111 '
1"
#22000
0"
#23000
b10010000 &
b1011001 !
b1011001 %
b1011001 '
1"
#24000
0"
#25000
b11101001 &
b10010000 !
b10010000 %
b10010000 '
1"
#26000
0"
#27000
b101111001 &
b11101001 !
b11101001 %
b11101001 '
1"
#28000
0"
#29000
b1001100010 &
b101111001 !
b101111001 %
b101111001 '
1"
#30000
0"
#31000
b1111011011 &
b1001100010 !
b1001100010 %
b1001100010 '
1"
#32000
0"
#33000
b11000111101 &
b1111011011 !
b1111011011 %
b1111011011 '
1"
#34000
0"
0#
#35000
b101000011000 &
b11000111101 !
b11000111101 %
b11000111101 '
1"
#36000
0"
1#
#37000
b1010101 &
b101000011000 !
b101000011000 %
b101000011000 '
1"
#38000
0"
#39000
b101001101101 &
b1010101 !
b1010101 %
b1010101 '
1"
#40000
0"
#41000
b101011000010 &
b101001101101 !
b101001101101 %
b101001101101 '
1"
#42000
0"
#43000
b10100101111 &
b101011000010 !
b101011000010 %
b101011000010 '
1"
#44000
0"
#45000
b111111110001 &
b10100101111 !
b10100101111 %
b10100101111 '
1"
#46000
0"
#47000
b10100100000 &
b111111110001 !
b111111110001 %
b111111110001 '
1"
#48000
0"
#49000
b10100010001 &
b10100100000 !
b10100100000 %
b10100100000 '
1"
#50000
0"
#51000
b101000110001 &
b10100010001 !
b10100010001 %
b10100010001 '
1"
#52000
0"
#53000
b111101000010 &
b101000110001 !
b101000110001 %
b101000110001 '
1"
#54000
0"
#55000
b100101110011 &
b111101000010 !
b111101000010 %
b111101000010 '
1"
#56000
0"
#57000
b100010110101 &
b100101110011 !
b100101110011 %
b100101110011 '
1"
#58000
0"
#59000
b1000101000 &
b100010110101 !
b100010110101 %
b100010110101 '
1"
#60000
0"
#61000
b101011011101 &
b1000101000 !
b1000101000 %
b1000101000 '
1"
#62000
0"
#63000
b110100000101 &
b101011011101 !
b101011011101 %
b101011011101 '
1"
#64000
0"
#65000
b11111100010 &
b110100000101 !
b110100000101 %
b110100000101 '
1"
#66000
0"
#67000
b10011100111 &
b11111100010 !
b11111100010 %
b11111100010 '
1"
#68000
0"
#69000
b110011001001 &
b10011100111 !
b10011100111 %
b10011100111 '
1"
#70000
0"
#71000
b110110000 &
b110011001001 !
b110011001001 %
b110011001001 '
1"
#72000
0"
#73000
b111001111001 &
b110110000 !
b110110000 %
b110110000 '
1"
#74000
0"
#75000
b101001 &
b111001111001 !
b111001111001 %
b111001111001 '
1"
