Verilog Assignments/Verilog Assignments Answers/Verilog HW2/B) SQRT_int/SQRT_int.v
// Computer Organization - IUST Spring 2023
// Verilog HW2 : 2
//-----------------------------------------
// Squared Root Module

module sqrt_int ( input      clk,
                  input      start,             // start signal
                  output     logic busy,              // calculation in progress
                  output     logic valid,             // root and rem are valid
                  input      [WIDTH-1:0] rad,   // radicand
                  output     logic [WIDTH-1:0] root,  // root
                  output     logic [WIDTH-1:0] rem    // remainder    
                );

    parameter WIDTH = 8;
    logic [WIDTH-1:0] x, x_next;    // radicand copy
    logic [WIDTH-1:0] q, q_next;    // intermediate root (quotient)
    logic [WIDTH+1:0] ac, ac_next;  // accumulator (2 bits wider)
    logic [WIDTH+1:0] test_res;     // sign test result (2 bits wider)

    localparam ITER = WIDTH >> 1;   // iterations are half radicand width
    logic [$clog2(ITER)-1:0] i;     // iteration counter

    always #10 begin
        test_res = ac - {q, 2'b01};
        if (test_res[WIDTH+1] == 0) begin  // test_res ≥0? (check MSB)
            {ac_next, x_next} = {test_res[WIDTH-1:0], x, 2'b0};
            q_next = {q[WIDTH-2:0], 1'b1};
        end else begin
            {ac_next, x_next} = {ac[WIDTH-1:0], x, 2'b0};
            q_next = q << 1;
        end
    end

    always @(posedge clk) begin
        if (start) begin
            busy <= 1;
            valid <= 0;
            i <= 0;
            q <= 0;
            {ac, x} <= {{WIDTH{1'b0}}, rad, 2'b0};
        end else if (busy) begin
            if (i == ITER-1) begin  // we're done
                busy <= 0;
                valid <= 1;
                root <= q_next;
                rem <= ac_next[WIDTH+1:2];  // undo final shift
            end else begin  // next iteration
                i <= i + 1;
                x <= x_next;
                ac <= ac_next;
                q <= q_next;
            end
        end
    end
endmodule

Verilog Assignments/Verilog Assignments Answers/Verilog HW2/B) SQRT_int/SQRT_int_tb.v
// Computer Organization - IUST Spring 2023
// Verilog HW2 : 2
//-----------------------------------------
// Squared Root Module testbench

`include "SQRT_int.v"
module sqrt_int_tb();

    parameter CLK_PERIOD = 10;
    parameter WIDTH = 8;
    reg clk;
    reg start;              // start signal
    wire busy;              // calculation in progress
    wire valid;             // root and rem are valid
    reg [WIDTH-1:0] rad;    // radicand
    wire [WIDTH-1:0] root;  // root
    wire [WIDTH-1:0] rem;   // remainder
    
    sqrt_int SQRT(clk, start, busy, valid, rad, root, rem); 

    always #(CLK_PERIOD / 2) clk = ~clk;

    initial begin
        $monitor("\t%d:\tsqrt(%d) =%d (rem =%d) (V=%b)", $time, rad, root, rem, valid);
    end

    initial begin
        $dumpfile("SQRT_int.vcd");
        $dumpvars(0,sqrt_int_tb);
        clk = 1;
        #100    rad = 8'b00000000;  // 0
                start = 1;
        #10     start = 0;
        #50     rad = 8'b00000001;  // 1
                start = 1;
        #10     start = 0;
        #50     rad = 8'b01111001;  // 121
                start = 1;
        #10     start = 0;
        #50     rad = 8'b01010001;  // 81
                start = 1;
        #10     start = 0;
        #50     rad = 8'b01011010;  // 90
                start = 1;
        #10     start = 0;
        #50     rad = 8'b11111111;  // 255
                start = 1;
        #10     start = 0;
        #50     $finish;
    end
endmodule

Verilog_Assignments/Verilog_HW2/Solutions/2_Square_Root_Integer/Square_Root.vcd
$date
	Sun Mar 19 20:00:50 2023
$end
$version
	Icarus Verilog
$end
$timescale
	1s
$end
$scope module sqrt_int_tb $end
$var wire 1 ! valid $end
$var wire 8 " root [7:0] $end
$var wire 8 # rem [7:0] $end
$var wire 1 $ busy $end
$var parameter 32 % CLK_PERIOD $end
$var parameter 32 & WIDTH $end
$var reg 1 ' clk $end
$var reg 8 ( rad [7:0] $end
$var reg 1 ) start $end
$scope module SQRT $end
$var wire 1 ' clk $end
$var wire 8 * rad [7:0] $end
$var wire 1 ) start $end
$var parameter 32 + ITER $end
$var parameter 32 , WIDTH $end
$var reg 10 - ac [9:0] $end
$var reg 10 . ac_next [9:0] $end
$var reg 1 $ busy $end
$var reg 2 / i [1:0] $end
$var reg 8 0 q [7:0] $end
$var reg 8 1 q_next [7:0] $end
$var reg 8 2 rem [7:0] $end
$var reg 8 3 root [7:0] $end
$var reg 10 4 test_res [9:0] $end
$var reg 1 ! valid $end
$var reg 8 5 x [7:0] $end
$var reg 8 6 x_next [7:0] $end
$upscope $end
$upscope $end
$enddefinitions $end
$comment Show the parameter values. $end
$dumpall
b1000 ,
b100 +
b1000 &
b1010 %
$end
#0
$dumpvars
bx 6
bx 5
bx 4
bx 3
bx 2
bx 1
bx 0
bx /
bx .
bx -
bx *
x)
bx (
1'
x$
bx #
bx "
x!
$end
#5
0'
#10
1'
bx0 1
bx00 6
#15
0'
#20
1'
#25
0'
#30
1'
#35
0'
#40
1'
#45
0'
#50
1'
#55
0'
#60
1'
#65
0'
#70
1'
#75
0'
#80
1'
#85
0'
#90
1'
#95
0'
#100
b0 -
b0 5
b0 0
b0 /
0!
1$
1'
1)
b0 (
b0 *
#105
0'
#110
b1 /
1'
b0 1
b0 .
b0 6
b1111111111 4
0)
#115
0'
#120
b10 /
1'
#125
0'
#130
b11 /
1'
#135
0'
#140
b0 #
b0 2
b0 "
b0 3
1!
0$
1'
#145
0'
#150
1'
#155
0'
#160
b100 5
b0 /
0!
1$
1'
1)
b1 (
b1 *
#165
0'
#170
b10000 5
b1 /
1'
b10000 6
0)
#175
0'
#180
b1000000 5
b10 /
1'
b1000000 6
#185
0'
#190
b1 -
b0 5
b11 /
1'
b1 .
b0 6
#195
0'
#200
b1 "
b1 3
1!
0$
1'
b1 1
b0 .
b0 4
#205
0'
#210
1'
#215
0'
#220
b11100100 5
b0 /
0!
1$
1'
1)
b1111001 (
b1111001 *
#225
0'
#230
b1 0
b11 -
b10010000 5
b1 /
1'
b11 .
b10010000 6
0)
#235
0'
#240
b10 0
b1110 -
b1000000 5
b10 /
1'
b10 1
b1110 .
b1000000 6
b1111111110 4
#245
0'
#250
b101 0
b10101 -
b0 5
b11 /
1'
b101 1
b10101 .
b0 6
b101 4
#255
0'
#260
b1011 "
b1011 3
1!
0$
1'
b1011 1
b0 .
b0 4
#265
0'
#270
1'
#275
0'
#280
b1 -
b1000100 5
b0 0
b0 /
0!
1$
1'
1)
b1010001 (
b1010001 *
#285
0'
#290
b1 0
b10000 5
b1 /
1'
b1 1
b1 .
b10000 6
0)
#295
0'
#300
b10 0
b100 -
b1000000 5
b10 /
1'
b10 1
b100 .
b1000000 6
b1111111100 4
#305
0'
#310
b100 0
b10001 -
b0 5
b11 /
1'
b100 1
b10001 .
b0 6
b1111111011 4
#315
0'
#320
b1001 "
b1001 3
1!
0$
1'
b1001 1
b0 .
b0 4
#325
0'
#330
1'
#335
0'
#340
b1 -
b1101000 5
b0 0
b0 /
0!
1$
1'
1)
b1011010 (
b1011010 *
#345
0'
#350
b1 0
b10100000 5
b1 /
1'
b1 1
b1 .
b10100000 6
0)
#355
0'
#360
b10 0
b110 -
b10000000 5
b10 /
1'
b10 1
b110 .
b10000000 6
b1111111100 4
#365
0'
#370
b100 0
b11010 -
b0 5
b11 /
1'
b100 1
b11010 .
b0 6
b1111111101 4
#375
0'
#380
b1001 #
b1001 2
1!
0$
1'
b1001 1
b100100 .
b1001 4
#385
0'
#390
1'
#395
0'
#400
b11 -
b11111100 5
b0 0
b0 /
0!
1$
1'
1)
b11111111 (
b11111111 *
#405
0'
#410
b1 0
b1011 -
b11110000 5
b1 /
1'
b1 1
b1011 .
b11110000 6
b10 4
0)
#415
0'
#420
b11 0
b11011 -
b11000000 5
b10 /
1'
b11 1
b11011 .
b11000000 6
b110 4
#425
0'
#430
b111 0
b111011 -
b0 5
b11 /
1'
b111 1
b111011 .
b0 6
b1110 4
#435
0'
#440
b11110 #
b11110 2
b1111 "
b1111 3
1!
0$
1'
b1111 1
b1111000 .
b11110 4
