Calculator_Pipeline/Arithmetic_Logic_Unit.v
module Arithmetic_Logic_Unit #(
    parameter DATA_WIDTH = 18
) (
    input [1 : 0] Operation,
    input [7 : 0] Operand_1,
    input [7 : 0] Operand_2,
    output reg [DATA_WIDTH - 1 : 0] Result
);
    always @(*)
    begin
        case (Operation)
            2'b00 : Result = Operand_1 + Operand_2;
            2'b01 : Result = Operand_1 - Operand_2;
            2'b10 : Result = Operand_1 * Operand_2;
            2'b11 : Result = Operand_1 / Operand_2; 
        endcase    
    end
endmodule

Calculator_Pipeline/Control_Unit.v
module Control_Unit (
    input [17 : 0] Instruction,
    output [1 : 0] Operation,
    output [7 : 0] Operand_1,
    output [7 : 0] Operand_2
);
    assign Operation = Instruction[17 : 16];
    assign Operand_1 = Instruction[15 : 8];
    assign Operand_2 = Instruction[7 : 0];    
endmodule

Calculator_Pipeline/Fetch_Unit.v
module Fetch_Unit #(
    parameter ADDRESS_WIDTH = 10,
    parameter DATA_WIDTH = 18
) (
    input Enable,
    input [ADDRESS_WIDTH - 1 : 0] Address,
    output [DATA_WIDTH - 1 : 0]  Data
);
    reg [DATA_WIDTH - 1 : 0] Memory [0 : $pow(2, ADDRESS_WIDTH) - 1];

    initial $readmemb("Memory.txt", Memory);   

    assign Data = Enable ? Memory[Address] : 'bz;
endmodule

Calculator_Pipeline/Core.v
`include "Fetch_Unit.v"
`include "Control_Unit.v"
`include "Arithmetic_Logic_Unit.v"

module Core #(
    parameter ADDRESS_WIDTH = 10,
    parameter DATA_WIDTH = 18
) (
    input Reset,
    input CLK,
    output [DATA_WIDTH - 1 : 0] Result
);
    reg [ADDRESS_WIDTH - 1 : 0] ProgramCounter;

    wire    [DATA_WIDTH - 1 : 0] Instruction_S0;
    reg     [DATA_WIDTH - 1 : 0] Instruction_S1;

    wire    [1 : 0] Operation_S1;
    reg     [1 : 0] Operation_S2;

    wire    [7 : 0] Operand_1_S1;
    reg     [7 : 0] Operand_1_S2;

    wire    [7 : 0] Operand_2_S1;
    reg     [7 : 0] Operand_2_S2;

    Fetch_Unit #(ADDRESS_WIDTH, DATA_WIDTH) fetch_unit (
        .Enable(1'b1),
        .Address(ProgramCounter),
        .Data(Instruction_S0)
    );

    Control_Unit control_unit (
        .Instruction(Instruction_S1),
        .Operation(Operation_S1),
        .Operand_1(Operand_1_S1),
        .Operand_2(Operand_2_S1)
    );

    Arithmetic_Logic_Unit #(DATA_WIDTH) alu (
        .Operation(Operation_S2),
        .Operand_1(Operand_1_S2),
        .Operand_2(Operand_2_S2),
        .Result(Result)
    );
    
    always @(posedge CLK)
        ProgramCounter <= Reset ? 'b0 : ProgramCounter + 1;
    
    always @(posedge CLK)
        Instruction_S1 <= Instruction_S0;
    
    always @(posedge CLK)
    begin
        Operation_S2 <= Operation_S1;
        Operand_1_S2 <= Operand_1_S1;
        Operand_2_S2 <= Operand_2_S1;
    end

endmodule

Calculator_Pipeline/Core_Testbench.v
`timescale 1ns/1ns
`include "Core.v"

module Core_Testbench;
    parameter ADDRESS_WIDTH = 10;
    parameter DATA_WIDTH = 18;

    parameter State = 1;
    parameter T = 2;

    reg Reset  = 1;
    reg CLK = 0;
    always #(T / 2) CLK = ~CLK;

    wire [DATA_WIDTH - 1 : 0] Result;

    Core #(ADDRESS_WIDTH, DATA_WIDTH) uut (
        .Reset(Reset),
        .CLK(CLK),
        .Result(Result)
    );

    initial
    begin
        $dumpfile("Core.vcd");
        $dumpvars(0, Core_Testbench);
        #(T)
        Reset = 0;
        for (integer i = 0; i < 100; i = i + 1)
        begin
            # (T * State);
        end
        $finish;
    end
endmodule

Calculator_Pipeline/Core.vcd
$date
	Sat May 06 11:43:41 2023
$end
$version
	Icarus Verilog
$end
$timescale
	1ns
$end
$scope module Core_Testbench $end
$var wire 18 ! Result [17:0] $end
$var parameter 32 " ADDRESS_WIDTH $end
$var parameter 32 # DATA_WIDTH $end
$var parameter 32 $ State $end
$var parameter 32 % T $end
$var reg 1 & CLK $end
$var reg 1 ' Reset $end
$scope module uut $end
$var wire 1 & CLK $end
$var wire 1 ' Reset $end
$var wire 18 ( Result [17:0] $end
$var wire 2 ) Operation_S1 [1:0] $end
$var wire 8 * Operand_2_S1 [7:0] $end
$var wire 8 + Operand_1_S1 [7:0] $end
$var wire 18 , Instruction_S0 [17:0] $end
$var parameter 32 - ADDRESS_WIDTH $end
$var parameter 32 . DATA_WIDTH $end
$var reg 18 / Instruction_S1 [17:0] $end
$var reg 8 0 Operand_1_S2 [7:0] $end
$var reg 8 1 Operand_2_S2 [7:0] $end
$var reg 2 2 Operation_S2 [1:0] $end
$var reg 10 3 ProgramCounter [9:0] $end
$scope module alu $end
$var wire 8 4 Operand_1 [7:0] $end
$var wire 8 5 Operand_2 [7:0] $end
$var wire 2 6 Operation [1:0] $end
$var parameter 32 7 DATA_WIDTH $end
$var reg 18 8 Result [17:0] $end
$upscope $end
$scope module control_unit $end
$var wire 18 9 Instruction [17:0] $end
$var wire 2 : Operation [1:0] $end
$var wire 8 ; Operand_2 [7:0] $end
$var wire 8 < Operand_1 [7:0] $end
$upscope $end
$scope module fetch_unit $end
$var wire 10 = Address [9:0] $end
$var wire 18 > Data [17:0] $end
$var wire 1 ? Enable $end
$var parameter 32 @ ADDRESS_WIDTH $end
$var parameter 32 A DATA_WIDTH $end
$upscope $end
$upscope $end
$scope begin $ivl_for_loop0 $end
$var integer 32 B i [31:0] $end
$upscope $end
$upscope $end
$enddefinitions $end
$comment Show the parameter values. $end
$dumpall
b10010 A
b1010 @
b10010 7
b10010 .
b1010 -
b10 %
b1 $
b10010 #
b1010 "
$end
#0
$dumpvars
bx B
1?
bx >
bx =
bx <
bx ;
bx :
bx 9
bx 8
bx 6
bx 5
bx 4
bx 3
bx 2
bx 1
bx 0
bx /
bx ,
bx +
bx *
bx )
bx (
1'
0&
bx !
$end
#1
b110010111110110001 ,
b110010111110110001 >
b0 3
b0 =
1&
#2
0&
b0 B
0'
#3
b11 )
b11 :
b101111 +
b101111 <
b10110001 *
b10110001 ;
b110010111110110001 /
b110010111110110001 9
b10111110010101110 ,
b10111110010101110 >
b1 3
b1 =
1&
#4
0&
b1 B
#5
b1 )
b1 :
b1111100 +
b1111100 <
b10101110 *
b10101110 ;
b0 !
b0 (
b0 8
b110101110011110110 ,
b110101110011110110 >
b10 3
b10 =
b10111110010101110 /
b10111110010101110 9
b10110001 1
b10110001 5
b101111 0
b101111 4
b11 2
b11 6
1&
#6
0&
b10 B
#7
b111111111111001110 !
b111111111111001110 (
b111111111111001110 8
b11 )
b11 :
b1011100 +
b1011100 <
b11110110 *
b11110110 ;
b10101110 1
b10101110 5
b1111100 0
b1111100 4
b1 2
b1 6
b110101110011110110 /
b110101110011110110 9
b10011101100001011 ,
b10011101100001011 >
b11 3
b11 =
1&
#8
0&
b11 B
#9
b1 )
b1 :
b111011 +
b111011 <
b1011 *
b1011 ;
b0 !
b0 (
b0 8
b11001010010111001 ,
b11001010010111001 >
b100 3
b100 =
b10011101100001011 /
b10011101100001011 9
b11110110 1
b11110110 5
b1011100 0
b1011100 4
b11 2
b11 6
1&
#10
0&
b100 B
#11
b110000 !
b110000 (
b110000 8
b10010100 +
b10010100 <
b10111001 *
b10111001 ;
b1011 1
b1011 5
b111011 0
b111011 4
b1 2
b1 6
b11001010010111001 /
b11001010010111001 9
b1000101000100110 ,
b1000101000100110 >
b101 3
b101 =
1&
#12
0&
b101 B
#13
b0 )
b0 :
b10001010 +
b10001010 <
b100110 *
b100110 ;
b111111111111011011 !
b111111111111011011 (
b111111111111011011 8
b101111011001110011 ,
b101111011001110011 >
b110 3
b110 =
b1000101000100110 /
b1000101000100110 9
b10111001 1
b10111001 5
b10010100 0
b10010100 4
1&
#14
0&
b110 B
#15
b10110000 !
b10110000 (
b10110000 8
b10 )
b10 :
b11110110 +
b11110110 <
b1110011 *
b1110011 ;
b100110 1
b100110 5
b10001010 0
b10001010 4
b0 2
b0 6
b101111011001110011 /
b101111011001110011 9
b11000011110111 ,
b11000011110111 >
b111 3
b111 =
1&
#16
0&
b111 B
#17
b0 )
b0 :
b110000 +
b110000 <
b11110111 *
b11110111 ;
b110111010000010 !
b110111010000010 (
b110111010000010 8
b10001110110110100 ,
b10001110110110100 >
b1000 3
b1000 =
b11000011110111 /
b11000011110111 9
b1110011 1
b1110011 5
b11110110 0
b11110110 4
b10 2
b10 6
1&
#18
0&
b1000 B
#19
b100100111 !
b100100111 (
b100100111 8
b1 )
b1 :
b11101 +
b11101 <
b10110100 *
b10110100 ;
b11110111 1
b11110111 5
b110000 0
b110000 4
b0 2
b0 6
b10001110110110100 /
b10001110110110100 9
b11001000011011101 ,
b11001000011011101 >
b1001 3
b1001 =
1&
#20
0&
b1001 B
#21
b10010000 +
b10010000 <
b11011101 *
b11011101 ;
b111111111101101001 !
b111111111101101001 (
b111111111101101001 8
b101110100101110010 ,
b101110100101110010 >
b1010 3
b1010 =
b11001000011011101 /
b11001000011011101 9
b10110100 1
b10110100 5
b11101 0
b11101 4
b1 2
b1 6
1&
#22
0&
b1010 B
#23
b111111111110110011 !
b111111111110110011 (
b111111111110110011 8
b10 )
b10 :
b11101001 +
b11101001 <
b1110010 *
b1110010 ;
b11011101 1
b11011101 5
b10010000 0
b10010000 4
b101110100101110010 /
b101110100101110010 9
b101001101011110101 ,
b101001101011110101 >
b1011 3
b1011 =
1&
#24
0&
b1011 B
#25
b10011010 +
b10011010 <
b11110101 *
b11110101 ;
b110011111000010 !
b110011111000010 (
b110011111000010 8
b110001101111110110 ,
b110001101111110110 >
b1100 3
b1100 =
b101001101011110101 /
b101001101011110101 9
b1110010 1
b1110010 5
b11101001 0
b11101001 4
b10 2
b10 6
1&
#26
0&
b1100 B
#27
b1001001101100010 !
b1001001101100010 (
b1001001101100010 8
b11 )
b11 :
b11011 +
b11011 <
b11110110 *
b11110110 ;
b11110101 1
b11110101 5
b10011010 0
b10011010 4
b110001101111110110 /
b110001101111110110 9
b111001011010001010 ,
b111001011010001010 >
b1101 3
b1101 =
1&
#28
0&
b1101 B
#29
b10010110 +
b10010110 <
b10001010 *
b10001010 ;
b0 !
b0 (
b0 8
b11010101001111100 ,
b11010101001111100 >
b1110 3
b1110 =
b111001011010001010 /
b111001011010001010 9
b11110110 1
b11110110 5
b11011 0
b11011 4
b11 2
b11 6
1&
#30
0&
b1110 B
#31
b1 !
b1 (
b1 8
b1 )
b1 :
b10101010 +
b10101010 <
b1111100 *
b1111100 ;
b10001010 1
b10001010 5
b10010110 0
b10010110 4
b11010101001111100 /
b11010101001111100 9
b110100000110100010 ,
b110100000110100010 >
b1111 3
b1111 =
1&
#32
0&
b1111 B
#33
b11 )
b11 :
b1000001 +
b1000001 <
b10100010 *
b10100010 ;
b101110 !
b101110 (
b101110 8
b101010101111000011 ,
b101010101111000011 >
b10000 3
b10000 =
b110100000110100010 /
b110100000110100010 9
b1111100 1
b1111100 5
b10101010 0
b10101010 4
b1 2
b1 6
1&
#34
0&
b10000 B
#35
b0 !
b0 (
b0 8
b10 )
b10 :
b10101011 +
b10101011 <
b11000011 *
b11000011 ;
b10100010 1
b10100010 5
b1000001 0
b1000001 4
b11 2
b11 6
b101010101111000011 /
b101010101111000011 9
b1111110100110101 ,
b1111110100110101 >
b10001 3
b10001 =
1&
#36
0&
b10001 B
#37
b0 )
b0 :
b11111101 +
b11111101 <
b110101 *
b110101 ;
b1000001001000001 !
b1000001001000001 (
b1000001001000001 8
b1100010110101101 ,
b1100010110101101 >
b10010 3
b10010 =
b1111110100110101 /
b1111110100110101 9
b11000011 1
b11000011 5
b10101011 0
b10101011 4
b10 2
b10 6
1&
#38
0&
b10010 B
#39
b100110010 !
b100110010 (
b100110010 8
b11000101 +
b11000101 <
b10101101 *
b10101101 ;
b110101 1
b110101 5
b11111101 0
b11111101 4
b0 2
b0 6
b1100010110101101 /
b1100010110101101 9
b100100011110011 ,
b100100011110011 >
b10011 3
b10011 =
1&
#40
0&
b10011 B
#41
b1001000 +
b1001000 <
b11110011 *
b11110011 ;
b101110010 !
b101110010 (
b101110010 8
b101111111111000110 ,
b101111111111000110 >
b10100 3
b10100 =
b100100011110011 /
b100100011110011 9
b10101101 1
b10101101 5
b11000101 0
b11000101 4
1&
#42
0&
b10100 B
#43
b100111011 !
b100111011 (
b100111011 8
b10 )
b10 :
b11111111 +
b11111111 <
b11000110 *
b11000110 ;
b11110011 1
b11110011 5
b1001000 0
b1001000 4
b101111111111000110 /
b101111111111000110 9
b11111101111110100 ,
b11111101111110100 >
b10101 3
b10101 =
1&
#44
0&
b10101 B
#45
b1 )
b1 :
b11111011 +
b11111011 <
b11110100 *
b11110100 ;
b1100010100111010 !
b1100010100111010 (
b1100010100111010 8
b100010001011011001 ,
b100010001011011001 >
b10110 3
b10110 =
b11111101111110100 /
b11111101111110100 9
b11000110 1
b11000110 5
b11111111 0
b11111111 4
b10 2
b10 6
1&
#46
0&
b10110 B
#47
b111 !
b111 (
b111 8
b10 )
b10 :
b100010 +
b100010 <
b11011001 *
b11011001 ;
b11110100 1
b11110100 5
b11111011 0
b11111011 4
b1 2
b1 6
b100010001011011001 /
b100010001011011001 9
b10010010001001101 ,
b10010010001001101 >
b10111 3
b10111 =
1&
#48
0&
b10111 B
#49
b1 )
b1 :
b100100 +
b100100 <
b1001101 *
b1001101 ;
b1110011010010 !
b1110011010010 (
b1110011010010 8
b1010010111111010 ,
b1010010111111010 >
b11000 3
b11000 =
b10010010001001101 /
b10010010001001101 9
b11011001 1
b11011001 5
b100010 0
b100010 4
b10 2
b10 6
1&
#50
0&
b11000 B
#51
b111111111111010111 !
b111111111111010111 (
b111111111111010111 8
b0 )
b0 :
b10100101 +
b10100101 <
b11111010 *
b11111010 ;
b1001101 1
b1001101 5
b100100 0
b100100 4
b1 2
b1 6
b1010010111111010 /
b1010010111111010 9
b101100010010000111 ,
b101100010010000111 >
b11001 3
b11001 =
1&
#52
0&
b11001 B
#53
b10 )
b10 :
b11000100 +
b11000100 <
b10000111 *
b10000111 ;
b110011111 !
b110011111 (
b110011111 8
b1101001000000100 ,
b1101001000000100 >
b11010 3
b11010 =
b101100010010000111 /
b101100010010000111 9
b11111010 1
b11111010 5
b10100101 0
b10100101 4
b0 2
b0 6
1&
#54
0&
b11010 B
#55
b110011101011100 !
b110011101011100 (
b110011101011100 8
b0 )
b0 :
b11010010 +
b11010010 <
b100 *
b100 ;
b10000111 1
b10000111 5
b11000100 0
b11000100 4
b10 2
b10 6
b1101001000000100 /
b1101001000000100 9
b110011110011010100 ,
b110011110011010100 >
b11011 3
b11011 =
1&
#56
0&
b11011 B
#57
b11 )
b11 :
b111100 +
b111100 <
b11010100 *
b11010100 ;
b11010110 !
b11010110 (
b11010110 8
b100110111011011000 ,
b100110111011011000 >
b11100 3
b11100 =
b110011110011010100 /
b110011110011010100 9
b100 1
b100 5
b11010010 0
b11010010 4
b0 2
b0 6
1&
#58
0&
b11100 B
#59
b0 !
b0 (
b0 8
b10 )
b10 :
b1101110 +
b1101110 <
b11011000 *
b11011000 ;
b11010100 1
b11010100 5
b111100 0
b111100 4
b11 2
b11 6
b100110111011011000 /
b100110111011011000 9
b111010111011111 ,
b111010111011111 >
b11101 3
b11101 =
1&
#60
0&
b11101 B
#61
b0 )
b0 :
b1110101 +
b1110101 <
b11011111 *
b11011111 ;
b101110011010000 !
b101110011010000 (
b101110011010000 8
b111110111101010111 ,
b111110111101010111 >
b11110 3
b11110 =
b111010111011111 /
b111010111011111 9
b11011000 1
b11011000 5
b1101110 0
b1101110 4
b10 2
b10 6
1&
#62
0&
b11110 B
#63
b101010100 !
b101010100 (
b101010100 8
b11 )
b11 :
b11101111 +
b11101111 <
b1010111 *
b1010111 ;
b11011111 1
b11011111 5
b1110101 0
b1110101 4
b0 2
b0 6
b111110111101010111 /
b111110111101010111 9
b100110100101101010 ,
b100110100101101010 >
b11111 3
b11111 =
1&
#64
0&
b11111 B
#65
b10 )
b10 :
b1101001 +
b1101001 <
b1101010 *
b1101010 ;
b10 !
b10 (
b10 8
b10111010010 ,
b10111010010 >
b100000 3
b100000 =
b100110100101101010 /
b100110100101101010 9
b1010111 1
b1010111 5
b11101111 0
b11101111 4
b11 2
b11 6
1&
#66
0&
b100000 B
#67
b10101101111010 !
b10101101111010 (
b10101101111010 8
b0 )
b0 :
b101 +
b101 <
b11010010 *
b11010010 ;
b1101010 1
b1101010 5
b1101001 0
b1101001 4
b10 2
b10 6
b10111010010 /
b10111010010 9
b100110001011010000 ,
b100110001011010000 >
b100001 3
b100001 =
1&
#68
0&
b100001 B
#69
b10 )
b10 :
b1100010 +
b1100010 <
b11010000 *
b11010000 ;
b11010111 !
b11010111 (
b11010111 8
b10011101011011010 ,
b10011101011011010 >
b100010 3
b100010 =
b100110001011010000 /
b100110001011010000 9
b11010010 1
b11010010 5
b101 0
b101 4
b0 2
b0 6
1&
#70
0&
b100010 B
#71
b100111110100000 !
b100111110100000 (
b100111110100000 8
b1 )
b1 :
b111010 +
b111010 <
b11011010 *
b11011010 ;
b11010000 1
b11010000 5
b1100010 0
b1100010 4
b10 2
b10 6
b10011101011011010 /
b10011101011011010 9
b10101011010000001 ,
b10101011010000001 >
b100011 3
b100011 =
1&
#72
0&
b100011 B
#73
b1010110 +
b1010110 <
b10000001 *
b10000001 ;
b111111111101100000 !
b111111111101100000 (
b111111111101100000 8
b101010011100010100 ,
b101010011100010100 >
b100100 3
b100100 =
b10101011010000001 /
b10101011010000001 9
b11011010 1
b11011010 5
b111010 0
b111010 4
b1 2
b1 6
1&
#74
0&
b100100 B
#75
b111111111111010101 !
b111111111111010101 (
b111111111111010101 8
b10 )
b10 :
b10100111 +
b10100111 <
b10100 *
b10100 ;
b10000001 1
b10000001 5
b1010110 0
b1010110 4
b101010011100010100 /
b101010011100010100 9
b100000110011000110 ,
b100000110011000110 >
b100101 3
b100101 =
1&
#76
0&
b100101 B
#77
b1100 +
b1100 <
b11000110 *
b11000110 ;
b110100001100 !
b110100001100 (
b110100001100 8
b11010110111101101 ,
b11010110111101101 >
b100110 3
b100110 =
b100000110011000110 /
b100000110011000110 9
b10100 1
b10100 5
b10100111 0
b10100111 4
b10 2
b10 6
1&
#78
0&
b100110 B
#79
b100101001000 !
b100101001000 (
b100101001000 8
b1 )
b1 :
b10101101 +
b10101101 <
b11101101 *
b11101101 ;
b11000110 1
b11000110 5
b1100 0
b1100 4
b11010110111101101 /
b11010110111101101 9
b111110011111010 ,
b111110011111010 >
b100111 3
b100111 =
1&
#80
0&
b100111 B
#81
b0 )
b0 :
b1111100 +
b1111100 <
b11111010 *
b11111010 ;
b111111111111000000 !
b111111111111000000 (
b111111111111000000 8
b11101100111111010 ,
b11101100111111010 >
b101000 3
b101000 =
b111110011111010 /
b111110011111010 9
b11101101 1
b11101101 5
b10101101 0
b10101101 4
b1 2
b1 6
1&
#82
0&
b101000 B
#83
b101110110 !
b101110110 (
b101110110 8
b1 )
b1 :
b11011001 +
b11011001 <
b11111010 1
b11111010 5
b1111100 0
b1111100 4
b0 2
b0 6
b11101100111111010 /
b11101100111111010 9
b100011101110001000 ,
b100011101110001000 >
b101001 3
b101001 =
1&
#84
0&
b101001 B
#85
b10 )
b10 :
b111011 +
b111011 <
b10001000 *
b10001000 ;
b111111111111011111 !
b111111111111011111 (
b111111111111011111 8
b101110111000000010 ,
b101110111000000010 >
b101010 3
b101010 =
b100011101110001000 /
b100011101110001000 9
b11011001 0
b11011001 4
b1 2
b1 6
1&
#86
0&
b101010 B
#87
b1111101011000 !
b1111101011000 (
b1111101011000 8
b11101110 +
b11101110 <
b10 *
b10 ;
b10001000 1
b10001000 5
b111011 0
b111011 4
b10 2
b10 6
b101110111000000010 /
b101110111000000010 9
b1010001111110010 ,
b1010001111110010 >
b101011 3
b101011 =
1&
#88
0&
b101011 B
#89
b0 )
b0 :
b10100011 +
b10100011 <
b11110010 *
b11110010 ;
b111011100 !
b111011100 (
b111011100 8
b111100010001001111 ,
b111100010001001111 >
b101100 3
b101100 =
b1010001111110010 /
b1010001111110010 9
b10 1
b10 5
b11101110 0
b11101110 4
1&
#90
0&
b101100 B
#91
b110010101 !
b110010101 (
b110010101 8
b11 )
b11 :
b11000100 +
b11000100 <
b1001111 *
b1001111 ;
b11110010 1
b11110010 5
b10100011 0
b10100011 4
b0 2
b0 6
b111100010001001111 /
b111100010001001111 9
b10101100000 ,
b10101100000 >
b101101 3
b101101 =
1&
#92
0&
b101101 B
#93
b0 )
b0 :
b101 +
b101 <
b1100000 *
b1100000 ;
b10 !
b10 (
b10 8
b100111011000110001 ,
b100111011000110001 >
b101110 3
b101110 =
b10101100000 /
b10101100000 9
b1001111 1
b1001111 5
b11000100 0
b11000100 4
b11 2
b11 6
1&
#94
0&
b101110 B
#95
b1100101 !
b1100101 (
b1100101 8
b10 )
b10 :
b1110110 +
b1110110 <
b110001 *
b110001 ;
b1100000 1
b1100000 5
b101 0
b101 4
b0 2
b0 6
b100111011000110001 /
b100111011000110001 9
b101010110001001101 ,
b101010110001001101 >
b101111 3
b101111 =
1&
#96
0&
b101111 B
#97
b10101100 +
b10101100 <
b1001101 *
b1001101 ;
b1011010010110 !
b1011010010110 (
b1011010010110 8
b101111010101100100 ,
b101111010101100100 >
b110000 3
b110000 =
b101010110001001101 /
b101010110001001101 9
b110001 1
b110001 5
b1110110 0
b1110110 4
b10 2
b10 6
1&
#98
0&
b110000 B
#99
b11001110111100 !
b11001110111100 (
b11001110111100 8
b11110101 +
b11110101 <
b1100100 *
b1100100 ;
b1001101 1
b1001101 5
b10101100 0
b10101100 4
b101111010101100100 /
b101111010101100100 9
b11010101011100110 ,
b11010101011100110 >
b110001 3
b110001 =
1&
#100
0&
b110001 B
#101
b1 )
b1 :
b10101010 +
b10101010 <
b11100110 *
b11100110 ;
b101111110110100 !
b101111110110100 (
b101111110110100 8
b110011110010011010 ,
b110011110010011010 >
b110010 3
b110010 =
b11010101011100110 /
b11010101011100110 9
b1100100 1
b1100100 5
b11110101 0
b11110101 4
1&
#102
0&
b110010 B
#103
b111111111111000100 !
b111111111111000100 (
b111111111111000100 8
b11 )
b11 :
b111100 +
b111100 <
b10011010 *
b10011010 ;
b11100110 1
b11100110 5
b10101010 0
b10101010 4
b1 2
b1 6
b110011110010011010 /
b110011110010011010 9
b100101101111010000 ,
b100101101111010000 >
b110011 3
b110011 =
1&
#104
0&
b110011 B
#105
b10 )
b10 :
b1011011 +
b1011011 <
b11010000 *
b11010000 ;
b0 !
b0 (
b0 8
b111100000011111101 ,
b111100000011111101 >
b110100 3
b110100 =
b100101101111010000 /
b100101101111010000 9
b10011010 1
b10011010 5
b111100 0
b111100 4
b11 2
b11 6
1&
#106
0&
b110100 B
#107
b100100111110000 !
b100100111110000 (
b100100111110000 8
b11 )
b11 :
b11000000 +
b11000000 <
b11111101 *
b11111101 ;
b11010000 1
b11010000 5
b1011011 0
b1011011 4
b10 2
b10 6
b111100000011111101 /
b111100000011111101 9
b11100010011111101 ,
b11100010011111101 >
b110101 3
b110101 =
1&
#108
0&
b110101 B
#109
b1 )
b1 :
b11000100 +
b11000100 <
b0 !
b0 (
b0 8
b100011011101101011 ,
b100011011101101011 >
b110110 3
b110110 =
b11100010011111101 /
b11100010011111101 9
b11111101 1
b11111101 5
b11000000 0
b11000000 4
b11 2
b11 6
1&
#110
0&
b110110 B
#111
b111111111111000111 !
b111111111111000111 (
b111111111111000111 8
b10 )
b10 :
b110111 +
b110111 <
b1101011 *
b1101011 ;
b11000100 0
b11000100 4
b1 2
b1 6
b100011011101101011 /
b100011011101101011 9
b111000100010011010 ,
b111000100010011010 >
b110111 3
b110111 =
1&
#112
0&
b110111 B
#113
b11 )
b11 :
b10001000 +
b10001000 <
b10011010 *
b10011010 ;
b1011011111101 !
b1011011111101 (
b1011011111101 8
b101100001101000 ,
b101100001101000 >
b111000 3
b111000 =
b111000100010011010 /
b111000100010011010 9
b1101011 1
b1101011 5
b110111 0
b110111 4
b10 2
b10 6
1&
#114
0&
b111000 B
#115
b0 !
b0 (
b0 8
b0 )
b0 :
b1011000 +
b1011000 <
b1101000 *
b1101000 ;
b10011010 1
b10011010 5
b10001000 0
b10001000 4
b11 2
b11 6
b101100001101000 /
b101100001101000 9
b110000011100001010 ,
b110000011100001010 >
b111001 3
b111001 =
1&
#116
0&
b111001 B
#117
b11 )
b11 :
b111 +
b111 <
b1010 *
b1010 ;
b11000000 !
b11000000 (
b11000000 8
b111100110011101110 ,
b111100110011101110 >
b111010 3
b111010 =
b110000011100001010 /
b110000011100001010 9
b1101000 1
b1101000 5
b1011000 0
b1011000 4
b0 2
b0 6
1&
#118
0&
b111010 B
#119
b0 !
b0 (
b0 8
b11001100 +
b11001100 <
b11101110 *
b11101110 ;
b1010 1
b1010 5
b111 0
b111 4
b11 2
b11 6
b111100110011101110 /
b111100110011101110 9
b110010000001110100 ,
b110010000001110100 >
b111011 3
b111011 =
1&
#120
0&
b111011 B
#121
b100000 +
b100000 <
b1110100 *
b1110100 ;
b100111011101 ,
b100111011101 >
b111100 3
b111100 =
b110010000001110100 /
b110010000001110100 9
b11101110 1
b11101110 5
b11001100 0
b11001100 4
1&
#122
0&
b111100 B
#123
b0 )
b0 :
b1001 +
b1001 <
b11011101 *
b11011101 ;
b1110100 1
b1110100 5
b100000 0
b100000 4
b100111011101 /
b100111011101 9
b111100101000111000 ,
b111100101000111000 >
b111101 3
b111101 =
1&
#124
0&
b111101 B
#125
b11 )
b11 :
b11001010 +
b11001010 <
b111000 *
b111000 ;
b11100110 !
b11100110 (
b11100110 8
b100001010011000000 ,
b100001010011000000 >
b111110 3
b111110 =
b111100101000111000 /
b111100101000111000 9
b11011101 1
b11011101 5
b1001 0
b1001 4
b0 2
b0 6
1&
#126
0&
b111110 B
#127
b11 !
b11 (
b11 8
b10 )
b10 :
b10100 +
b10100 <
b11000000 *
b11000000 ;
b111000 1
b111000 5
b11001010 0
b11001010 4
b11 2
b11 6
b100001010011000000 /
b100001010011000000 9
b10001010100110110 ,
b10001010100110110 >
b111111 3
b111111 =
1&
#128
0&
b111111 B
#129
b1 )
b1 :
b10101 +
b10101 <
b110110 *
b110110 ;
b111100000000 !
b111100000000 (
b111100000000 8
b110011011111111000 ,
b110011011111111000 >
b1000000 3
b1000000 =
b10001010100110110 /
b10001010100110110 9
b11000000 1
b11000000 5
b10100 0
b10100 4
b10 2
b10 6
1&
#130
0&
b1000000 B
#131
b111111111111011111 !
b111111111111011111 (
b111111111111011111 8
b11 )
b11 :
b110111 +
b110111 <
b11111000 *
b11111000 ;
b110110 1
b110110 5
b10101 0
b10101 4
b1 2
b1 6
b110011011111111000 /
b110011011111111000 9
b10001101001011 ,
b10001101001011 >
b1000001 3
b1000001 =
1&
#132
0&
b1000001 B
#133
b0 )
b0 :
b100011 +
b100011 <
b1001011 *
b1001011 ;
b0 !
b0 (
b0 8
b101111110100100010 ,
b101111110100100010 >
b1000010 3
b1000010 =
b10001101001011 /
b10001101001011 9
b11111000 1
b11111000 5
b110111 0
b110111 4
b11 2
b11 6
1&
#134
0&
b1000010 B
#135
b1101110 !
b1101110 (
b1101110 8
b10 )
b10 :
b11111101 +
b11111101 <
b100010 *
b100010 ;
b1001011 1
b1001011 5
b100011 0
b100011 4
b0 2
b0 6
b101111110100100010 /
b101111110100100010 9
b11110100011111111 ,
b11110100011111111 >
b1000011 3
b1000011 =
1&
#136
0&
b1000011 B
#137
b1 )
b1 :
b11101000 +
b11101000 <
b11111111 *
b11111111 ;
b10000110011010 !
b10000110011010 (
b10000110011010 8
b1010011011001010 ,
b1010011011001010 >
b1000100 3
b1000100 =
b11110100011111111 /
b11110100011111111 9
b100010 1
b100010 5
b11111101 0
b11111101 4
b10 2
b10 6
1&
#138
0&
b1000100 B
#139
b111111111111101001 !
b111111111111101001 (
b111111111111101001 8
b0 )
b0 :
b10100110 +
b10100110 <
b11001010 *
b11001010 ;
b11111111 1
b11111111 5
b11101000 0
b11101000 4
b1 2
b1 6
b1010011011001010 /
b1010011011001010 9
b110101100000101001 ,
b110101100000101001 >
b1000101 3
b1000101 =
1&
#140
0&
b1000101 B
#141
b11 )
b11 :
b1011000 +
b1011000 <
b101001 *
b101001 ;
b101110000 !
b101110000 (
b101110000 8
b10100110000100000 ,
b10100110000100000 >
b1000110 3
b1000110 =
b110101100000101001 /
b110101100000101001 9
b11001010 1
b11001010 5
b10100110 0
b10100110 4
b0 2
b0 6
1&
#142
0&
b1000110 B
#143
b10 !
b10 (
b10 8
b1 )
b1 :
b1001100 +
b1001100 <
b100000 *
b100000 ;
b101001 1
b101001 5
b1011000 0
b1011000 4
b11 2
b11 6
b10100110000100000 /
b10100110000100000 9
b10101011000010110 ,
b10101011000010110 >
b1000111 3
b1000111 =
1&
#144
0&
b1000111 B
#145
b1010110 +
b1010110 <
b10110 *
b10110 ;
b101100 !
b101100 (
b101100 8
b101001000110000011 ,
b101001000110000011 >
b1001000 3
b1001000 =
b10101011000010110 /
b10101011000010110 9
b100000 1
b100000 5
b1001100 0
b1001100 4
b1 2
b1 6
1&
#146
0&
b1001000 B
#147
b1000000 !
b1000000 (
b1000000 8
b10 )
b10 :
b10010001 +
b10010001 <
b10000011 *
b10000011 ;
b10110 1
b10110 5
b1010110 0
b1010110 4
b101001000110000011 /
b101001000110000011 9
b10111110100111 ,
b10111110100111 >
b1001001 3
b1001001 =
1&
#148
0&
b1001001 B
#149
b0 )
b0 :
b101111 +
b101111 <
b10100111 *
b10100111 ;
b100101000110011 !
b100101000110011 (
b100101000110011 8
b110100111001101 ,
b110100111001101 >
b1001010 3
b1001010 =
b10111110100111 /
b10111110100111 9
b10000011 1
b10000011 5
b10010001 0
b10010001 4
b10 2
b10 6
1&
